llm_tracekit/__init__.py
llm_tracekit/coralogix.py
llm_tracekit/extended_gen_ai_attributes.py
llm_tracekit/instrumentation_utils.py
llm_tracekit/instruments.py
llm_tracekit/py.typed
llm_tracekit/span_builder.py
llm_tracekit/bedrock/__init__.py
llm_tracekit/bedrock/converse.py
llm_tracekit/bedrock/instrumentor.py
llm_tracekit/bedrock/invoke_agent.py
llm_tracekit/bedrock/invoke_model.py
llm_tracekit/bedrock/package.py
llm_tracekit/bedrock/parsing_utils.py
llm_tracekit/bedrock/patch.py
llm_tracekit/bedrock/utils.py
llm_tracekit/gemini/__init__.py
llm_tracekit/gemini/instrumentor.py
llm_tracekit/gemini/package.py
llm_tracekit/gemini/patch.py
llm_tracekit/gemini/state.py
llm_tracekit/gemini/utils.py
llm_tracekit/langchain/__init__.py
llm_tracekit/langchain/callback.py
llm_tracekit/langchain/instrumentor.py
llm_tracekit/langchain/package.py
llm_tracekit/langchain/span_manager.py
llm_tracekit/langchain/utils.py
llm_tracekit/litellm/__init__.py
llm_tracekit/litellm/callback.py
llm_tracekit/litellm/instrumentor.py
llm_tracekit/litellm/package.py
llm_tracekit/openai/__init__.py
llm_tracekit/openai/instrumentor.py
llm_tracekit/openai/package.py
llm_tracekit/openai/patch.py
llm_tracekit/openai/utils.py
llm_tracekit/openai_agents/__init__.py
llm_tracekit/openai_agents/instrumentor.py
llm_tracekit/openai_agents/package.py
llm_tracekit/openai_agents/tracing_processor.py
llm_tracekit-1.7.0.dist-info/METADATA
llm_tracekit-1.7.0.dist-info/WHEEL
llm_tracekit-1.7.0.dist-info/entry_points.txt
llm_tracekit-1.7.0.dist-info/RECORD
