Metadata-Version: 2.4
Name: llm-tracekit
Version: 1.7.0
Summary: Collect and send GenAI calls as spans for development and production observability.
Project-URL: homepage, https://coralogix.com
Project-URL: repository, https://github.com/coralogix/llm-tracekit.git
Author-email: "Coralogix Ltd." <info@coralogix.com>
License-Expression: Apache-2.0
Classifier: Development Status :: 5 - Production/Stable
Classifier: Framework :: OpenTelemetry :: Instrumentations
Classifier: Intended Audience :: Developers
Classifier: License :: OSI Approved :: Apache Software License
Classifier: Programming Language :: Python :: 3
Classifier: Programming Language :: Python :: 3.8
Classifier: Programming Language :: Python :: 3.9
Classifier: Programming Language :: Python :: 3.10
Classifier: Programming Language :: Python :: 3.11
Classifier: Programming Language :: Python :: 3.12
Classifier: Programming Language :: Python :: 3.13
Requires-Python: <=3.13,>3.9
Requires-Dist: opentelemetry-api>=1.32.1
Requires-Dist: opentelemetry-exporter-otlp>=1.32.1
Requires-Dist: opentelemetry-instrumentation>=0.53b1
Requires-Dist: opentelemetry-sdk>=1.32.1
Requires-Dist: opentelemetry-semantic-conventions>=0.53b1
Provides-Extra: bedrock
Requires-Dist: boto3>=1.36.0; extra == 'bedrock'
Provides-Extra: ci-core
Requires-Dist: boto3>=1.36.0; extra == 'ci-core'
Requires-Dist: google-genai<2,>=1.0.0; extra == 'ci-core'
Requires-Dist: langchain-aws>=1.0.0; (python_version >= '3.10') and extra == 'ci-core'
Requires-Dist: langchain-openai>=1.0.0; (python_version >= '3.10') and extra == 'ci-core'
Requires-Dist: langchain>=1.0.0; (python_version >= '3.10') and extra == 'ci-core'
Requires-Dist: openai-agents>=0.1.0; (python_version >= '3.10') and extra == 'ci-core'
Requires-Dist: openai>=1.26.0; extra == 'ci-core'
Provides-Extra: gemini
Requires-Dist: google-genai<2,>=1.0.0; extra == 'gemini'
Provides-Extra: langchain
Requires-Dist: langchain>=1.0.0; (python_version >= '3.10') and extra == 'langchain'
Provides-Extra: langchain-all
Requires-Dist: langchain-aws>=1.0.0; (python_version >= '3.10') and extra == 'langchain-all'
Requires-Dist: langchain-openai>=1.0.0; (python_version >= '3.10') and extra == 'langchain-all'
Requires-Dist: langchain>=1.0.0; (python_version >= '3.10') and extra == 'langchain-all'
Provides-Extra: langchain-aws
Requires-Dist: langchain-aws>=1.0.0; (python_version >= '3.10') and extra == 'langchain-aws'
Requires-Dist: langchain>=1.0.0; (python_version >= '3.10') and extra == 'langchain-aws'
Provides-Extra: langchain-openai
Requires-Dist: langchain-openai>=1.0.0; (python_version >= '3.10') and extra == 'langchain-openai'
Requires-Dist: langchain>=1.0.0; (python_version >= '3.10') and extra == 'langchain-openai'
Provides-Extra: litellm
Requires-Dist: litellm[proxy]>=1.65.4; extra == 'litellm'
Provides-Extra: openai
Requires-Dist: openai>=1.26.0; extra == 'openai'
Provides-Extra: openai-agents
Requires-Dist: openai-agents>=0.1.0; (python_version >= '3.10') and extra == 'openai-agents'
Requires-Dist: openai>=1.26.0; extra == 'openai-agents'
